{
  "id" : "ea6f0abd-307d-4e22-b730-6f68211279dc",
  "name" : "edex-alr",
  "type" : "DERBY",
  "modelVersion" : "2.0",
  "storePath" : "${qpid.home_dir}${file.separator}edexalrMessageStore",
  "lastUpdatedBy" : "ANONYMOUS",
  "lastUpdatedTime" : 1439319374996,
  "createdBy" : "ANONYMOUS",
  "createdTime" : 1439319374996,
  "exchanges" : [ {
    "id" : "7dc12c05-f395-3fe4-82f7-850c3d5d6c09",
    "name" : "amq.direct",
    "type" : "direct",
    "lastUpdatedBy" : "ANONYMOUS",
    "lastUpdatedTime" : 1439319380726,
    "createdBy" : "ANONYMOUS",
    "createdTime" : 1439319380726
  }, {
    "id" : "8c6dbc8a-dfeb-3aba-ad66-1f872cef8e50",
    "name" : "amq.fanout",
    "type" : "fanout",
    "lastUpdatedBy" : "ANONYMOUS",
    "lastUpdatedTime" : 1439319380729,
    "createdBy" : "ANONYMOUS",
    "createdTime" : 1439319380729
  }, {
    "id" : "a17fc850-3a37-383b-82a7-4c9c7d0a73dd",
    "name" : "amq.match",
    "type" : "headers",
    "lastUpdatedBy" : "ANONYMOUS",
    "lastUpdatedTime" : 1439319380728,
    "createdBy" : "ANONYMOUS",
    "createdTime" : 1439319380728
  }, {
    "id" : "b57d5da4-de41-38bc-ba67-f54c291e0909",
    "name" : "amq.topic",
    "type" : "topic",
    "lastUpdatedBy" : "ANONYMOUS",
    "lastUpdatedTime" : 1439319380727,
    "createdBy" : "ANONYMOUS",
    "createdTime" : 1439319380727
  } ],
  "queues" : [ {
    "id" : "77b457e8-dfba-45d3-825c-f788f72c2533",
    "name" : "Ingest.Shef",
    "durable" : true,
    "lifetimePolicy" : "PERMANENT",
    "exclusive" : "NONE",
    "owner" : null,
    "lastUpdatedBy" : "ANONYMOUS",
    "lastUpdatedTime" : 1439322450576,
    "createdBy" : "ANONYMOUS",
    "createdTime" : 1439322450576,
    "bindings" : [ {
      "exchange" : "7dc12c05-f395-3fe4-82f7-850c3d5d6c09",
      "id" : "abdc4caf-90a8-4282-886c-47979d6bfbdc",
      "name" : "Ingest.Shef",
      "durable" : true,
      "lastUpdatedBy" : "ANONYMOUS",
      "lastUpdatedTime" : 1439322450597,
      "createdBy" : "ANONYMOUS",
      "createdTime" : 1439322450597
    } ]
  }, {
    "id" : "27d76e70-973e-4d0a-91eb-179405c31f40",
    "name" : "Ingest.ShefManual",
    "durable" : true,
    "lifetimePolicy" : "PERMANENT",
    "exclusive" : "NONE",
    "owner" : null,
    "lastUpdatedBy" : "ANONYMOUS",
    "lastUpdatedTime" : 1439322450577,
    "createdBy" : "ANONYMOUS",
    "createdTime" : 1439322450577,
    "bindings" : [ {
      "exchange" : "7dc12c05-f395-3fe4-82f7-850c3d5d6c09",
      "id" : "a768a4bd-58d8-41ab-adc6-50cb83a9c2ac",
      "name" : "Ingest.ShefManual",
      "durable" : true,
      "lastUpdatedBy" : "ANONYMOUS",
      "lastUpdatedTime" : 1439322450599,
      "createdBy" : "ANONYMOUS",
      "createdTime" : 1439322450599
    } ]
  }, {
    "id" : "57937ee7-9ce6-4a96-bf6b-8653ad5841d9",
    "name" : "Ingest.ShefStaged",
    "durable" : true,
    "lifetimePolicy" : "PERMANENT",
    "exclusive" : "NONE",
    "owner" : null,
    "lastUpdatedBy" : "ANONYMOUS",
    "lastUpdatedTime" : 1439322450577,
    "createdBy" : "ANONYMOUS",
    "createdTime" : 1439322450577,
    "bindings" : [ {
      "exchange" : "7dc12c05-f395-3fe4-82f7-850c3d5d6c09",
      "id" : "761d33a9-c286-43a5-9d4f-36703a7f2be3",
      "name" : "Ingest.ShefStaged",
      "durable" : true,
      "lastUpdatedBy" : "ANONYMOUS",
      "lastUpdatedTime" : 1439322450605,
      "createdBy" : "ANONYMOUS",
      "createdTime" : 1439322450605
    } ]
  }, {
    "id" : "2009b847-a7c3-4ce1-b6c7-99e70877a795",
    "name" : "Ingest.bufrobs",
    "durable" : true,
    "lifetimePolicy" : "PERMANENT",
    "exclusive" : "NONE",
    "owner" : null,
    "lastUpdatedBy" : "ANONYMOUS",
    "lastUpdatedTime" : 1439322450576,
    "createdBy" : "ANONYMOUS",
    "createdTime" : 1439322450576,
    "bindings" : [ {
      "exchange" : "7dc12c05-f395-3fe4-82f7-850c3d5d6c09",
      "id" : "b01082d0-2450-4383-9d2a-cf9fa0d89207",
      "name" : "Ingest.bufrobs",
      "durable" : true,
      "lastUpdatedBy" : "ANONYMOUS",
      "lastUpdatedTime" : 1439322450610,
      "createdBy" : "ANONYMOUS",
      "createdTime" : 1439322450610
    } ]
  }, {
    "id" : "1eeed0c0-6162-40e9-a42b-d2a3ff32baac",
    "name" : "Ingest.dhr",
    "durable" : true,
    "lifetimePolicy" : "PERMANENT",
    "exclusive" : "NONE",
    "owner" : null,
    "lastUpdatedBy" : "ANONYMOUS",
    "lastUpdatedTime" : 1439322450577,
    "createdBy" : "ANONYMOUS",
    "createdTime" : 1439322450577,
    "bindings" : [ {
      "exchange" : "7dc12c05-f395-3fe4-82f7-850c3d5d6c09",
      "id" : "408e3f27-cd38-4404-bc64-8d71942dfe11",
      "name" : "Ingest.dhr",
      "durable" : true,
      "lastUpdatedBy" : "ANONYMOUS",
      "lastUpdatedTime" : 1439322450624,
      "createdBy" : "ANONYMOUS",
      "createdTime" : 1439322450624
    } ]
  }, {
    "id" : "56702a89-731a-4a55-865f-f2709ea8aea2",
    "name" : "Ingest.dpa",
    "durable" : true,
    "lifetimePolicy" : "PERMANENT",
    "exclusive" : "NONE",
    "owner" : null,
    "lastUpdatedBy" : "ANONYMOUS",
    "lastUpdatedTime" : 1439322450576,
    "createdBy" : "ANONYMOUS",
    "createdTime" : 1439322450576,
    "bindings" : [ {
      "exchange" : "7dc12c05-f395-3fe4-82f7-850c3d5d6c09",
      "id" : "a0226410-d58c-441f-a7d1-099f4568e10f",
      "name" : "Ingest.dpa",
      "durable" : true,
      "lastUpdatedBy" : "ANONYMOUS",
      "lastUpdatedTime" : 1439322450616,
      "createdBy" : "ANONYMOUS",
      "createdTime" : 1439322450616
    } ]
  }, {
    "id" : "a8d109b4-3697-42c8-809a-45f34e5f0121",
    "name" : "Ingest.manual",
    "durable" : true,
    "lifetimePolicy" : "PERMANENT",
    "exclusive" : "NONE",
    "owner" : null,
    "lastUpdatedBy" : "ANONYMOUS",
    "lastUpdatedTime" : 1439321926785,
    "createdBy" : "ANONYMOUS",
    "createdTime" : 1439321926785,
    "bindings" : [ {
      "exchange" : "7dc12c05-f395-3fe4-82f7-850c3d5d6c09",
      "id" : "aeb96bfe-fb80-4b04-9928-197e24c4e01d",
      "name" : "Ingest.manual",
      "durable" : true,
      "lastUpdatedBy" : "ANONYMOUS",
      "lastUpdatedTime" : 1439321926804,
      "createdBy" : "ANONYMOUS",
      "createdTime" : 1439321926804
    } ]
  }, {
    "id" : "761e4649-0870-47f2-99e1-6788e64fcf41",
    "name" : "Ingest.obs",
    "durable" : true,
    "lifetimePolicy" : "PERMANENT",
    "exclusive" : "NONE",
    "owner" : null,
    "lastUpdatedBy" : "ANONYMOUS",
    "lastUpdatedTime" : 1439322450577,
    "createdBy" : "ANONYMOUS",
    "createdTime" : 1439322450577,
    "bindings" : [ {
      "exchange" : "7dc12c05-f395-3fe4-82f7-850c3d5d6c09",
      "id" : "5db89bae-ed12-4475-a3ae-710f6949b6da",
      "name" : "Ingest.obs",
      "durable" : true,
      "lastUpdatedBy" : "ANONYMOUS",
      "lastUpdatedTime" : 1439322450619,
      "createdBy" : "ANONYMOUS",
      "createdTime" : 1439322450619
    } ]
  }, {
    "id" : "1e3e7c3a-0ab0-46b4-b1de-1599d96775b4",
    "name" : "Ingest.q2",
    "durable" : true,
    "lifetimePolicy" : "PERMANENT",
    "exclusive" : "NONE",
    "owner" : null,
    "lastUpdatedBy" : "ANONYMOUS",
    "lastUpdatedTime" : 1439322450576,
    "createdBy" : "ANONYMOUS",
    "createdTime" : 1439322450576,
    "bindings" : [ {
      "exchange" : "7dc12c05-f395-3fe4-82f7-850c3d5d6c09",
      "id" : "1075c5e6-db52-44b6-a856-6b446552b540",
      "name" : "Ingest.q2",
      "durable" : true,
      "lastUpdatedBy" : "ANONYMOUS",
      "lastUpdatedTime" : 1439322450603,
      "createdBy" : "ANONYMOUS",
      "createdTime" : 1439322450603
    } ]
  }, {
    "id" : "f7361905-2bde-42bf-94d0-78d8e3379927",
    "name" : "Ingest.sfcobs",
    "durable" : true,
    "lifetimePolicy" : "PERMANENT",
    "exclusive" : "NONE",
    "owner" : null,
    "lastUpdatedBy" : "ANONYMOUS",
    "lastUpdatedTime" : 1439322450578,
    "createdBy" : "ANONYMOUS",
    "createdTime" : 1439322450578,
    "bindings" : [ {
      "exchange" : "7dc12c05-f395-3fe4-82f7-850c3d5d6c09",
      "id" : "caa85188-c1cf-4500-8019-ff95a7b60a8b",
      "name" : "Ingest.sfcobs",
      "durable" : true,
      "lastUpdatedBy" : "ANONYMOUS",
      "lastUpdatedTime" : 1439322450621,
      "createdBy" : "ANONYMOUS",
      "createdTime" : 1439322450621
    } ]
  }, {
    "id" : "c7aa5ebf-3d4b-49ea-843c-f7c3b2bf82bb",
    "name" : "dhrProcess",
    "durable" : true,
    "lifetimePolicy" : "PERMANENT",
    "exclusive" : "NONE",
    "owner" : null,
    "lastUpdatedBy" : "ANONYMOUS",
    "lastUpdatedTime" : 1439322450576,
    "createdBy" : "ANONYMOUS",
    "createdTime" : 1439322450576,
    "bindings" : [ {
      "exchange" : "7dc12c05-f395-3fe4-82f7-850c3d5d6c09",
      "id" : "d42167d8-9dab-4232-8570-ec76d24357ba",
      "name" : "dhrProcess",
      "durable" : true,
      "lastUpdatedBy" : "ANONYMOUS",
      "lastUpdatedTime" : 1439322450591,
      "createdBy" : "ANONYMOUS",
      "createdTime" : 1439322450591
    } ]
  }, {
    "id" : "ec1f46d7-d962-4dec-80ff-6a75f9c54997",
    "name" : "external.dropbox",
    "durable" : true,
    "lifetimePolicy" : "PERMANENT",
    "exclusive" : "NONE",
    "owner" : null,
    "lastUpdatedBy" : "ANONYMOUS",
    "lastUpdatedTime" : 1439322450576,
    "createdBy" : "ANONYMOUS",
    "createdTime" : 1439322450576,
    "bindings" : [ {
      "exchange" : "7dc12c05-f395-3fe4-82f7-850c3d5d6c09",
      "id" : "e46d0c1d-61d2-406d-9cf9-9b85afdf65b8",
      "name" : "external.dropbox",
      "durable" : true,
      "lastUpdatedBy" : "ANONYMOUS",
      "lastUpdatedTime" : 1439322450595,
      "createdBy" : "ANONYMOUS",
      "createdTime" : 1439322450595
    } ]
  }, {
    "id" : "62df0808-6fc4-49ff-95ac-d97a1e5372ee",
    "name" : "handleoup.dropbox",
    "durable" : true,
    "lifetimePolicy" : "PERMANENT",
    "exclusive" : "NONE",
    "owner" : null,
    "lastUpdatedBy" : "ANONYMOUS",
    "lastUpdatedTime" : 1439322450576,
    "createdBy" : "ANONYMOUS",
    "createdTime" : 1439322450576,
    "bindings" : [ {
      "exchange" : "7dc12c05-f395-3fe4-82f7-850c3d5d6c09",
      "id" : "4ba08240-1a9c-4a1c-b7ec-ec47bb3e42a3",
      "name" : "handleoup.dropbox",
      "durable" : true,
      "lastUpdatedBy" : "ANONYMOUS",
      "lastUpdatedTime" : 1439322450586,
      "createdBy" : "ANONYMOUS",
      "createdTime" : 1439322450586
    } ]
  }, {
    "id" : "bd5e9bab-05ec-42d5-9686-05e14fe1a5c8",
    "name" : "radarserver.dropbox",
    "durable" : true,
    "lifetimePolicy" : "PERMANENT",
    "exclusive" : "NONE",
    "owner" : null,
    "lastUpdatedBy" : "ANONYMOUS",
    "lastUpdatedTime" : 1439322450577,
    "createdBy" : "ANONYMOUS",
    "createdTime" : 1439322450577,
    "bindings" : [ {
      "exchange" : "7dc12c05-f395-3fe4-82f7-850c3d5d6c09",
      "id" : "b395ca02-ea5a-4f8d-a21c-513bcfc3c5fe",
      "name" : "radarserver.dropbox",
      "durable" : true,
      "lastUpdatedBy" : "ANONYMOUS",
      "lastUpdatedTime" : 1439322450607,
      "createdBy" : "ANONYMOUS",
      "createdTime" : 1439322450607
    } ]
  } ]
}
